jps_pre_commit_utils/__init__.py
jps_pre_commit_utils/check_inserted_lines.py
jps_pre_commit_utils/cli.py
jps_pre_commit_utils/config.py
jps_pre_commit_utils/git_diff.py
jps_pre_commit_utils/help.py
jps_pre_commit_utils/report.py
jps_pre_commit_utils/rules.py
jps_pre_commit_utils/scanner.py
jps_pre_commit_utils-1.3.0.dist-info/licenses/LICENSE
jps_pre_commit_utils-1.3.0.dist-info/METADATA
jps_pre_commit_utils-1.3.0.dist-info/WHEEL
jps_pre_commit_utils-1.3.0.dist-info/entry_points.txt
jps_pre_commit_utils-1.3.0.dist-info/top_level.txt
jps_pre_commit_utils-1.3.0.dist-info/RECORD
